pygex/__init__.py
pygex/__main__.py
pygex/vmath.py
pygex/animation/__init__.py
pygex/animation/animator.py
pygex/animation/curves.py
pygex/animation/target_animator.py
pygex/core/__init__.py
pygex/core/application.py
pygex/core/game_object.py
pygex/core/input.py
pygex/rendering/__init__.py
pygex/rendering/font.py
pygex/rendering/geometry.py
pygex/rendering/render_target.py
pygex/rendering/renderer.py
pygex/rendering/shader.py
pygex/rendering/texture.py
pygex/rendering/texture_generators.py
pygex/rendering/utils.py
pygex-0.1.9.dist-info/METADATA
pygex-0.1.9.dist-info/WHEEL
pygex-0.1.9.dist-info/top_level.txt
pygex-0.1.9.dist-info/RECORD
